{
    "tileGrid": {
        "x": 15,
        "y": 8
    },
    "buildings": [
        {
            "Center": {
                "x": 474.6711730957031,
                "y": 0.24529995024204255,
                "z": -285.64434814453127
            },
            "HalfSize": {
                "x": 3.87481427192688,
                "y": 0.24529995024204255,
                "z": 5.909572124481201
            },
            "Angle": 56.68937301635742
        },
        {
            "Center": {
                "x": 517.87060546875,
                "y": 0.24529995024204255,
                "z": -226.54510498046876
            },
            "HalfSize": {
                "x": 4.366716384887695,
                "y": 0.24529995024204255,
                "z": 1.4389443397521973
            },
            "Angle": 2.6025619506835939
        },
        {
            "Center": {
                "x": 455.76123046875,
                "y": 0.24529995024204255,
                "z": -272.49237060546877
            },
            "HalfSize": {
                "x": 3.128912925720215,
                "y": 0.24529995024204255,
                "z": 6.117558002471924
            },
            "Angle": 57.38853454589844
        },
        {
            "Center": {
                "x": 463.1182861328125,
                "y": 6.950165271759033,
                "z": -285.6489562988281
            },
            "HalfSize": {
                "x": 0.3520730435848236,
                "y": 6.950165271759033,
                "z": 0.5180428624153137
            },
            "Angle": 55.56114959716797
        },
        {
            "Center": {
                "x": 522.1631469726563,
                "y": 10.956730842590332,
                "z": -252.49197387695313
            },
            "HalfSize": {
                "x": 1.859210729598999,
                "y": 10.956730842590332,
                "z": 1.1611027717590333
            },
            "Angle": 57.901092529296878
        },
        {
            "Center": {
                "x": 503.13671875,
                "y": 0.24529995024204255,
                "z": -264.37469482421877
            },
            "HalfSize": {
                "x": 6.564562797546387,
                "y": 0.24529995024204255,
                "z": 9.019124984741211
            },
            "Angle": 56.397010803222659
        },
        {
            "Center": {
                "x": 501.764404296875,
                "y": 9.81199836730957,
                "z": -232.8580780029297
            },
            "HalfSize": {
                "x": 3.440218925476074,
                "y": 9.81199836730957,
                "z": 3.786734104156494
            },
            "Angle": 55.407684326171878
        },
        {
            "Center": {
                "x": 435.7294921875,
                "y": 6.377798557281494,
                "z": -185.94451904296876
            },
            "HalfSize": {
                "x": 0.566679835319519,
                "y": 6.377798557281494,
                "z": 3.272348642349243
            },
            "Angle": 85.236328125
        },
        {
            "Center": {
                "x": 490.86865234375,
                "y": 12.264997482299805,
                "z": -251.48406982421876
            },
            "HalfSize": {
                "x": 5.020927429199219,
                "y": 12.264997482299805,
                "z": 3.0474939346313478
            },
            "Angle": 57.31486511230469
        },
        {
            "Center": {
                "x": 522.068115234375,
                "y": 15.290363311767579,
                "z": -265.83111572265627
            },
            "HalfSize": {
                "x": 3.865485191345215,
                "y": 15.290363311767579,
                "z": 2.6600899696350099
            },
            "Angle": 54.251983642578128
        }
    ]
}