{
    "tileGrid": {
        "x": 3,
        "y": 3
    },
    "buildings": [
        {
            "Center": {
                "x": -742.078125,
                "y": 0.24529995024204255,
                "z": -741.9381103515625
            },
            "HalfSize": {
                "x": 4.182196617126465,
                "y": 0.24529995024204255,
                "z": 2.68117094039917
            },
            "Angle": 29.0
        },
        {
            "Center": {
                "x": -726.8466186523438,
                "y": 0.24529995024204255,
                "z": -749.0007934570313
            },
            "HalfSize": {
                "x": 4.842861652374268,
                "y": 0.24529995024204255,
                "z": 2.718400001525879
            },
            "Angle": 29.0
        },
        {
            "Center": {
                "x": -741.82177734375,
                "y": 0.24529995024204255,
                "z": -757.4044189453125
            },
            "HalfSize": {
                "x": 6.278593063354492,
                "y": 0.24529995024204255,
                "z": 3.1818506717681886
            },
            "Angle": 29.0
        },
        {
            "Center": {
                "x": -741.4532470703125,
                "y": 0.24529995024204255,
                "z": -784.3103637695313
            },
            "HalfSize": {
                "x": 5.099341869354248,
                "y": 0.24529995024204255,
                "z": 2.209510326385498
            },
            "Angle": 9.462211608886719
        },
        {
            "Center": {
                "x": -755.78662109375,
                "y": 0.24529995024204255,
                "z": -758.6495361328125
            },
            "HalfSize": {
                "x": 3.5187735557556154,
                "y": 0.24529995024204255,
                "z": 1.7162444591522217
            },
            "Angle": 29.0
        },
        {
            "Center": {
                "x": -724.708251953125,
                "y": 0.24529995024204255,
                "z": -702.7689208984375
            },
            "HalfSize": {
                "x": 6.915146827697754,
                "y": 0.24529995024204255,
                "z": 1.3503062725067139
            },
            "Angle": 13.078132629394532
        },
        {
            "Center": {
                "x": -756.9800415039063,
                "y": 0.24529995024204255,
                "z": -753.2348022460938
            },
            "HalfSize": {
                "x": 3.608823299407959,
                "y": 0.24529995024204255,
                "z": 1.821731448173523
            },
            "Angle": 29.0
        },
        {
            "Center": {
                "x": -769.2315673828125,
                "y": 0.24529995024204255,
                "z": -781.3872680664063
            },
            "HalfSize": {
                "x": 5.918150424957275,
                "y": 0.24529995024204255,
                "z": 2.071051597595215
            },
            "Angle": 29.0
        },
        {
            "Center": {
                "x": -750.7822265625,
                "y": 0.24529995024204255,
                "z": -687.51513671875
            },
            "HalfSize": {
                "x": 2.96903657913208,
                "y": 0.24529995024204255,
                "z": 2.104564666748047
            },
            "Angle": 6.968156337738037
        },
        {
            "Center": {
                "x": -750.5316772460938,
                "y": 0.24529995024204255,
                "z": -785.58056640625
            },
            "HalfSize": {
                "x": 2.3670265674591066,
                "y": 0.24529995024204255,
                "z": 1.2309614419937134
            },
            "Angle": 29.0
        },
        {
            "Center": {
                "x": -683.0880126953125,
                "y": 0.24529995024204255,
                "z": -690.2144165039063
            },
            "HalfSize": {
                "x": 5.608100891113281,
                "y": 0.24529995024204255,
                "z": 4.385071754455566
            },
            "Angle": 4.650169372558594
        },
        {
            "Center": {
                "x": -722.6660766601563,
                "y": 0.24529995024204255,
                "z": -762.6708374023438
            },
            "HalfSize": {
                "x": 3.9686670303344728,
                "y": 0.24529995024204255,
                "z": 2.5188233852386476
            },
            "Angle": 29.0
        },
        {
            "Center": {
                "x": -751.55078125,
                "y": 0.24529995024204255,
                "z": -771.8575439453125
            },
            "HalfSize": {
                "x": 3.12374210357666,
                "y": 0.24529995024204255,
                "z": 1.8412455320358277
            },
            "Angle": 29.0
        },
        {
            "Center": {
                "x": -732.5847778320313,
                "y": 0.24529995024204255,
                "z": -733.425537109375
            },
            "HalfSize": {
                "x": 4.870970726013184,
                "y": 0.24529995024204255,
                "z": 1.9799563884735108
            },
            "Angle": 29.000001907348634
        },
        {
            "Center": {
                "x": -761.9319458007813,
                "y": 0.24529995024204255,
                "z": -765.4517211914063
            },
            "HalfSize": {
                "x": 3.4584312438964845,
                "y": 0.24529995024204255,
                "z": 1.6000839471817017
            },
            "Angle": 28.999998092651368
        },
        {
            "Center": {
                "x": -719.5537109375,
                "y": 0.24529995024204255,
                "z": -690.46337890625
            },
            "HalfSize": {
                "x": 1.6167268753051758,
                "y": 0.24529995024204255,
                "z": 2.934286594390869
            },
            "Angle": 13.190605163574219
        },
        {
            "Center": {
                "x": -749.7836303710938,
                "y": 0.24529995024204255,
                "z": -750.9417114257813
            },
            "HalfSize": {
                "x": 3.448795795440674,
                "y": 0.24529995024204255,
                "z": 1.7068474292755128
            },
            "Angle": 29.0
        },
        {
            "Center": {
                "x": -720.4341430664063,
                "y": 0.24529995024204255,
                "z": -685.6561889648438
            },
            "HalfSize": {
                "x": 0.28727948665618899,
                "y": 0.24529995024204255,
                "z": 0.06224384158849716
            },
            "Angle": 11.309738159179688
        },
        {
            "Center": {
                "x": -718.3472900390625,
                "y": 0.24529995024204255,
                "z": -697.8887329101563
            },
            "HalfSize": {
                "x": 1.514126181602478,
                "y": 0.24529995024204255,
                "z": 3.112614631652832
            },
            "Angle": 13.109214782714844
        },
        {
            "Center": {
                "x": -732.42236328125,
                "y": 0.24529995024204255,
                "z": -771.9429931640625
            },
            "HalfSize": {
                "x": 3.8370704650878908,
                "y": 0.24529995024204255,
                "z": 2.6590170860290529
            },
            "Angle": 29.0
        },
        {
            "Center": {
                "x": -750.3859252929688,
                "y": 0.24529995024204255,
                "z": -775.8097534179688
            },
            "HalfSize": {
                "x": 3.2802910804748537,
                "y": 0.24529995024204255,
                "z": 1.8327677249908448
            },
            "Angle": 29.0
        },
        {
            "Center": {
                "x": -760.1874389648438,
                "y": 0.24529995024204255,
                "z": -687.17041015625
            },
            "HalfSize": {
                "x": 2.9795360565185549,
                "y": 0.24529995024204255,
                "z": 1.8357025384902955
            },
            "Angle": 6.9682087898254398
        },
        {
            "Center": {
                "x": -754.4409790039063,
                "y": 0.24529995024204255,
                "z": -763.1835327148438
            },
            "HalfSize": {
                "x": 3.4251232147216799,
                "y": 0.24529995024204255,
                "z": 1.5241867303848267
            },
            "Angle": 29.0
        },
        {
            "Center": {
                "x": -759.3004150390625,
                "y": 0.24529995024204255,
                "z": -771.7476196289063
            },
            "HalfSize": {
                "x": 4.3109965324401859,
                "y": 0.24529995024204255,
                "z": 2.529815673828125
            },
            "Angle": 29.0
        },
        {
            "Center": {
                "x": -763.2014770507813,
                "y": 0.24529995024204255,
                "z": -760.8374633789063
            },
            "HalfSize": {
                "x": 3.4867424964904787,
                "y": 0.24529995024204255,
                "z": 1.7732267379760743
            },
            "Angle": 29.0
        },
        {
            "Center": {
                "x": -720.4257202148438,
                "y": 0.24529995024204255,
                "z": -776.6863403320313
            },
            "HalfSize": {
                "x": 4.835664749145508,
                "y": 0.24529995024204255,
                "z": 2.856034278869629
            },
            "Angle": 29.0
        },
        {
            "Center": {
                "x": -749.0291137695313,
                "y": 0.24529995024204255,
                "z": -779.9780883789063
            },
            "HalfSize": {
                "x": 3.2056760787963869,
                "y": 0.24529995024204255,
                "z": 1.7438770532608033
            },
            "Angle": 29.0
        },
        {
            "Center": {
                "x": -742.5552368164063,
                "y": 0.24529995024204255,
                "z": -739.2354736328125
            },
            "HalfSize": {
                "x": 4.194034099578857,
                "y": 0.24529995024204255,
                "z": 1.7729809284210206
            },
            "Angle": 29.0
        },
        {
            "Center": {
                "x": -752.5424194335938,
                "y": 0.24529995024204255,
                "z": -767.5921020507813
            },
            "HalfSize": {
                "x": 3.190239429473877,
                "y": 0.24529995024204255,
                "z": 1.7166047096252442
            },
            "Angle": 29.0
        },
        {
            "Center": {
                "x": -755.2791137695313,
                "y": 0.24529995024204255,
                "z": -746.0425415039063
            },
            "HalfSize": {
                "x": 5.182392120361328,
                "y": 0.24529995024204255,
                "z": 2.0144312381744386
            },
            "Angle": 29.0
        },
        {
            "Center": {
                "x": -773.4202270507813,
                "y": 0.24529995024204255,
                "z": -765.3883056640625
            },
            "HalfSize": {
                "x": 5.255524635314941,
                "y": 0.24529995024204255,
                "z": 2.8014931678771974
            },
            "Angle": 29.0
        },
        {
            "Center": {
                "x": -742.2490234375,
                "y": 0.24529995024204255,
                "z": -766.9503173828125
            },
            "HalfSize": {
                "x": 3.570479393005371,
                "y": 0.24529995024204255,
                "z": 3.2783727645874025
            },
            "Angle": 28.999998092651368
        },
        {
            "Center": {
                "x": -758.6746826171875,
                "y": 0.24529995024204255,
                "z": -696.102294921875
            },
            "HalfSize": {
                "x": 3.321892738342285,
                "y": 0.24529995024204255,
                "z": 3.0560312271118166
            },
            "Angle": 6.9109649658203129
        },
        {
            "Center": {
                "x": -688.7402954101563,
                "y": 0.24529995024204255,
                "z": -776.5154418945313
            },
            "HalfSize": {
                "x": 11.342220306396485,
                "y": 0.24529995024204255,
                "z": 4.182840347290039
            },
            "Angle": 29.0
        },
        {
            "Center": {
                "x": -771.3164672851563,
                "y": 0.24529995024204255,
                "z": -773.9964599609375
            },
            "HalfSize": {
                "x": 6.020155429840088,
                "y": 0.24529995024204255,
                "z": 2.648503303527832
            },
            "Angle": 29.0
        },
        {
            "Center": {
                "x": -731.78759765625,
                "y": 0.24529995024204255,
                "z": -735.9200439453125
            },
            "HalfSize": {
                "x": 5.183111190795898,
                "y": 0.24529995024204255,
                "z": 2.862752914428711
            },
            "Angle": 29.0
        },
        {
            "Center": {
                "x": -765.838623046875,
                "y": 6.541332244873047,
                "z": -751.5494995117188
            },
            "HalfSize": {
                "x": 3.254704236984253,
                "y": 6.541332244873047,
                "z": 3.6548523902893068
            },
            "Angle": 29.0
        },
        {
            "Center": {
                "x": -696.2001953125,
                "y": 0.24529995024204255,
                "z": -687.5567016601563
            },
            "HalfSize": {
                "x": 14.148452758789063,
                "y": 0.24529995024204255,
                "z": 9.994991302490235
            },
            "Angle": 29.0
        },
        {
            "Center": {
                "x": -777.2313842773438,
                "y": 0.24529995024204255,
                "z": -784.7150268554688
            },
            "HalfSize": {
                "x": 0.9797616600990295,
                "y": 0.24529995024204255,
                "z": 1.3087718486785889
            },
            "Angle": 28.999998092651368
        },
        {
            "Center": {
                "x": -774.96044921875,
                "y": 7.3589982986450199,
                "z": -754.222412109375
            },
            "HalfSize": {
                "x": 4.173002243041992,
                "y": 7.3589982986450199,
                "z": 3.178926944732666
            },
            "Angle": 29.0
        },
        {
            "Center": {
                "x": -706.2545776367188,
                "y": 0.24529995024204255,
                "z": -723.2063598632813
            },
            "HalfSize": {
                "x": 8.912981033325196,
                "y": 0.24529995024204255,
                "z": 6.5773024559021
            },
            "Angle": 29.000001907348634
        }
    ]
}