{
    "tileGrid": {
        "x": 7,
        "y": 2
    },
    "buildings": [
        {
            "Center": {
                "x": -335.8403015136719,
                "y": 0.24529995024204255,
                "z": -791.0714111328125
            },
            "HalfSize": {
                "x": 3.814915657043457,
                "y": 0.24529995024204255,
                "z": 1.5166305303573609
            },
            "Angle": 29.0
        },
        {
            "Center": {
                "x": -337.0673522949219,
                "y": 0.24529995024204255,
                "z": -786.7101440429688
            },
            "HalfSize": {
                "x": 4.490454196929932,
                "y": 0.24529995024204255,
                "z": 1.594124674797058
            },
            "Angle": 29.0
        },
        {
            "Center": {
                "x": -335.9257507324219,
                "y": 0.24529995024204255,
                "z": -802.4849853515625
            },
            "HalfSize": {
                "x": 5.337340354919434,
                "y": 0.24529995024204255,
                "z": 1.7831460237503052
            },
            "Angle": 29.0
        },
        {
            "Center": {
                "x": -346.2110900878906,
                "y": 0.24529995024204255,
                "z": -794.8283081054688
            },
            "HalfSize": {
                "x": 6.130400657653809,
                "y": 0.24529995024204255,
                "z": 2.2330400943756105
            },
            "Angle": 29.0
        },
        {
            "Center": {
                "x": -352.1662292480469,
                "y": 0.24529995024204255,
                "z": -785.728759765625
            },
            "HalfSize": {
                "x": 4.344581127166748,
                "y": 0.24529995024204255,
                "z": 2.3198893070220949
            },
            "Angle": 29.0
        },
        {
            "Center": {
                "x": -305.77777099609377,
                "y": 0.24529995024204255,
                "z": -878.16845703125
            },
            "HalfSize": {
                "x": 8.683069229125977,
                "y": 0.24529995024204255,
                "z": 4.744067192077637
            },
            "Angle": 12.680404663085938
        }
    ]
}