{
    "tileGrid": {
        "x": 9,
        "y": 15
    },
    "buildings": [
        {
            "Center": {
                "x": -175.5999755859375,
                "y": 5.8871989250183109,
                "z": 415.04461669921877
            },
            "HalfSize": {
                "x": 0.7596629858016968,
                "y": 5.8871989250183109,
                "z": 2.254240036010742
            },
            "Angle": 88.36341857910156
        },
        {
            "Center": {
                "x": -110.86709594726563,
                "y": 0.24529995024204255,
                "z": 490.4920959472656
            },
            "HalfSize": {
                "x": 3.536205291748047,
                "y": 0.24529995024204255,
                "z": 3.295644760131836
            },
            "Angle": 29.0
        },
        {
            "Center": {
                "x": -151.7383575439453,
                "y": 0.24529995024204255,
                "z": 456.48193359375
            },
            "HalfSize": {
                "x": 1.6696877479553223,
                "y": 0.24529995024204255,
                "z": 3.2796788215637209
            },
            "Angle": 48.893585205078128
        },
        {
            "Center": {
                "x": -165.8871612548828,
                "y": 0.24529995024204255,
                "z": 447.55328369140627
            },
            "HalfSize": {
                "x": 1.8787058591842652,
                "y": 0.24529995024204255,
                "z": 3.8216488361358644
            },
            "Angle": 48.86726379394531
        },
        {
            "Center": {
                "x": -124.17037963867188,
                "y": 0.24529995024204255,
                "z": 505.3152160644531
            },
            "HalfSize": {
                "x": 1.7090704441070557,
                "y": 0.24529995024204255,
                "z": 3.2282464504241945
            },
            "Angle": 45.0
        },
        {
            "Center": {
                "x": -103.76226806640625,
                "y": 0.24529995024204255,
                "z": 512.2379760742188
            },
            "HalfSize": {
                "x": 10.67651081085205,
                "y": 0.24529995024204255,
                "z": 8.331046104431153
            },
            "Angle": 29.0
        },
        {
            "Center": {
                "x": -119.35470581054688,
                "y": 0.24529995024204255,
                "z": 500.4873352050781
            },
            "HalfSize": {
                "x": 1.7004395723342896,
                "y": 0.24529995024204255,
                "z": 3.228248119354248
            },
            "Angle": 45.0
        },
        {
            "Center": {
                "x": -156.82603454589845,
                "y": 0.24529995024204255,
                "z": 449.4309997558594
            },
            "HalfSize": {
                "x": 4.736126899719238,
                "y": 0.24529995024204255,
                "z": 1.7283369302749634
            },
            "Angle": 48.45240783691406
        },
        {
            "Center": {
                "x": -158.3881378173828,
                "y": 0.24529995024204255,
                "z": 440.44781494140627
            },
            "HalfSize": {
                "x": 2.586907386779785,
                "y": 0.24529995024204255,
                "z": 6.213449954986572
            },
            "Angle": 47.39115905761719
        },
        {
            "Center": {
                "x": -142.4152069091797,
                "y": 0.24529995024204255,
                "z": 446.00811767578127
            },
            "HalfSize": {
                "x": 2.956434965133667,
                "y": 0.24529995024204255,
                "z": 2.051044225692749
            },
            "Angle": 47.60255432128906
        },
        {
            "Center": {
                "x": -114.49630737304688,
                "y": 0.24529995024204255,
                "z": 495.6655578613281
            },
            "HalfSize": {
                "x": 1.7090718746185303,
                "y": 0.24529995024204255,
                "z": 3.2368764877319338
            },
            "Angle": 45.0
        },
        {
            "Center": {
                "x": -167.09967041015626,
                "y": 5.8871989250183109,
                "z": 414.5704345703125
            },
            "HalfSize": {
                "x": 0.6123425960540772,
                "y": 5.8871989250183109,
                "z": 3.7007040977478029
            },
            "Angle": 83.9276351928711
        },
        {
            "Center": {
                "x": -146.35960388183595,
                "y": 0.24529995024204255,
                "z": 452.4049377441406
            },
            "HalfSize": {
                "x": 1.75951087474823,
                "y": 0.24529995024204255,
                "z": 2.1033568382263185
            },
            "Angle": 45.29380798339844
        },
        {
            "Center": {
                "x": -151.70639038085938,
                "y": 7.6042985916137699,
                "z": 417.8792724609375
            },
            "HalfSize": {
                "x": 3.6820404529571535,
                "y": 7.6042985916137699,
                "z": 2.9932644367218019
            },
            "Angle": 28.999996185302736
        },
        {
            "Center": {
                "x": -142.54013061523438,
                "y": 0.24529995024204255,
                "z": 434.1429748535156
            },
            "HalfSize": {
                "x": 3.8835129737854006,
                "y": 0.24529995024204255,
                "z": 3.2570152282714845
            },
            "Angle": 48.296112060546878
        },
        {
            "Center": {
                "x": -175.28330993652345,
                "y": 0.24529995024204255,
                "z": 444.7037353515625
            },
            "HalfSize": {
                "x": 5.015241622924805,
                "y": 0.24529995024204255,
                "z": 6.139519691467285
            },
            "Angle": 29.0
        },
        {
            "Center": {
                "x": -148.35809326171876,
                "y": 0.24529995024204255,
                "z": 436.438232421875
            },
            "HalfSize": {
                "x": 4.282214164733887,
                "y": 0.24529995024204255,
                "z": 2.069251537322998
            },
            "Angle": 47.72639465332031
        },
        {
            "Center": {
                "x": -176.42520141601563,
                "y": 0.24529995024204255,
                "z": 464.54742431640627
            },
            "HalfSize": {
                "x": 4.198859691619873,
                "y": 0.24529995024204255,
                "z": 2.9578263759613039
            },
            "Angle": 55.422489166259769
        },
        {
            "Center": {
                "x": -147.81588745117188,
                "y": 0.24529995024204255,
                "z": 497.3953857421875
            },
            "HalfSize": {
                "x": 8.624512672424317,
                "y": 0.24529995024204255,
                "z": 6.583601951599121
            },
            "Angle": 29.0
        },
        {
            "Center": {
                "x": -134.9432373046875,
                "y": 0.24529995024204255,
                "z": 510.6544494628906
            },
            "HalfSize": {
                "x": 2.0139427185058595,
                "y": 0.24529995024204255,
                "z": 6.8534369468688969
            },
            "Angle": 83.66024017333985
        },
        {
            "Center": {
                "x": -161.048583984375,
                "y": 6.132498741149902,
                "z": 426.325927734375
            },
            "HalfSize": {
                "x": 2.478797435760498,
                "y": 6.132498741149902,
                "z": 6.216527938842773
            },
            "Angle": 81.12010192871094
        }
    ]
}